gcair/__init__.py
gcair/error.py
gcair/gc_air.py
gcair/get_sim_params.py
tests/__init__.py
tests/test_gcair.py
gcair-0.1.0.dist-info/LICENSE
gcair-0.1.0.dist-info/METADATA
gcair-0.1.0.dist-info/WHEEL
gcair-0.1.0.dist-info/top_level.txt
gcair-0.1.0.dist-info/RECORD
